modpin/README.rst
modpin/__init__.py
modpin/__init__.pyc
modpin/config_setup.py
modpin/config_setup.pyc
modpin/data/Compare_ddG_with_average_best_rank0_COMB.rank
modpin/data/Compare_ddG_with_average_best_rank0_ES3DC.rank
modpin/data/Compare_ddG_with_average_best_rank0_PAIR.rank
modpin/data/Compare_ddG_with_average_best_rank0_ZCOMB.rank
modpin/data/Compare_ddG_with_average_best_rank0_ZES3DC.rank
modpin/data/Compare_ddG_with_average_best_rank0_ZPAIR.rank
modpin/data/Compare_ddG_with_average_best_rank0_dGx_mean.rank
modpin/data/Compare_ddG_with_average_best_rank0_ddG_mean.rank
modpin/data/Compare_ddG_with_average_best_rank0_foldx.rank
modpin/data/Compare_ddG_with_average_best_rank0_zrank.rank
modpin/scripts/FilterHomologPairs.py
modpin/scripts/Renumerate.py
modpin/scripts/__init__.py
modpin/scripts/__init__.pyc
modpin/scripts/analysis.py
modpin/scripts/command_queue.txt
modpin/scripts/config.ini
modpin/scripts/modelist.py
modpin/scripts/modppi.py
modpin/scripts/modppi.pyc
modpin/src/__init__.py
modpin/src/BioLib/.DS_Store
modpin/src/BioLib/__init__.py
modpin/src/BioLib/__init__.pyc
modpin/src/BioLib/Algebra/Transforms.py
modpin/src/BioLib/Algebra/Transforms.pyc
modpin/src/BioLib/Algebra/__init__.py
modpin/src/BioLib/Algebra/__init__.pyc
modpin/src/BioLib/Docking/.DS_Store
modpin/src/BioLib/Docking/FTDock.py
modpin/src/BioLib/Docking/HEXDock.py
modpin/src/BioLib/Docking/HEXDock.pyc
modpin/src/BioLib/Docking/PATCHDock.py
modpin/src/BioLib/Docking/PATCHDock.pyc
modpin/src/BioLib/Docking/ScoringFunctions.py
modpin/src/BioLib/Docking/ScoringFunctions.pyc
modpin/src/BioLib/Docking/SplitPotentials.py
modpin/src/BioLib/Docking/SplitPotentials.pyc
modpin/src/BioLib/Docking/SplitPotentialsPPI.py
modpin/src/BioLib/Docking/SplitPotentialsPPI.pyc
modpin/src/BioLib/Docking/ZDock.py
modpin/src/BioLib/Docking/ZDock.pyc
modpin/src/BioLib/Docking/ZDock_create
modpin/src/BioLib/Docking/ZDock_create.cc
modpin/src/BioLib/Docking/__init__.py
modpin/src/BioLib/Docking/__init__.pyc
modpin-1.1.1.dist-info/METADATA
modpin-1.1.1.dist-info/WHEEL
modpin-1.1.1.dist-info/entry_points.txt
modpin-1.1.1.dist-info/top_level.txt
modpin-1.1.1.dist-info/RECORD
